api_requester/__init__.py
api_requester/core/__init__.py
api_requester/core/call_api.py
api_requester/core/admin/__init__.py
api_requester/core/admin/api/__init__.py
api_requester/core/admin/api/auth_api.py
api_requester/core/admin/api/ecoa_auth_api.py
api_requester/core/admin/api/subject_auth_api.py
api_requester/core/admin/api/user_on_board_application_api.py
api_requester/core/admin/dto/__init__.py
api_requester/core/admin/dto/cross_user_user_on_board_dto.py
api_requester/core/admin/dto/ecoa_onboard_request_dto.py
api_requester/core/admin/dto/jwt_authentication_request.py
api_requester/core/admin/dto/reset_password_email_request_dto.py
api_requester/core/admin/dto/sso_token_retrieve_dto.py
api_requester/core/admin/dto/subject_jwt_authentication_request.py
api_requester/core/admin/dto/user_on_board_dto.py
api_requester/core/admin/service/__init__.py
api_requester/core/admin/service/auth_service.py
api_requester/core/admin/service/ecoa_auth_service.py
api_requester/core/admin/service/subject_auth_service.py
api_requester/core/admin/service/user_on_board_application_service.py
api_requester/core/admin/service/impl/__init__.py
api_requester/core/admin/service/impl/system_env_service_impl.py
api_requester/core/admin/service/impl/user_on_board_application_service_impl.py
api_requester/core/common/__init__.py
api_requester/core/common/api/__init__.py
api_requester/core/common/api/ecoa_auth_api.py
api_requester/core/common/api/subject_auth_api.py
api_requester/core/common/api/system_env_api.py
api_requester/core/common/dto/portal_login_t_ime.py
api_requester/core/common/service/__init__.py
api_requester/core/common/service/ecoa_auth_service.py
api_requester/core/common/service/subject_auth_service.py
api_requester/core/common/service/system_env_service.py
api_requester/docs/application.yaml
api_requester/dto/__init__.py
api_requester/dto/base_dto.py
api_requester/dto/biz_base.py
api_requester/dto/user.py
api_requester/http/__init__.py
api_requester/http/app_url.py
eclinical_requester-1.0.18.dist-info/licenses/LICENSE
eclinical_requester-1.0.18.dist-info/METADATA
eclinical_requester-1.0.18.dist-info/WHEEL
eclinical_requester-1.0.18.dist-info/top_level.txt
eclinical_requester-1.0.18.dist-info/RECORD
