Metadata-Version: 2.4
Name: eclinical_requester
Version: 1.0.18
Summary: edetek api requester
Home-page: http://example.com
Author: xiaodong.li
Author-email: 
Classifier: Programming Language :: Python :: 3.9
License-File: LICENSE
Requires-Dist: lxml>=4.8.0
Requires-Dist: requests>=2.28.2
Requires-Dist: PyYAML>=6.0
Requires-Dist: requests-toolbelt>=0.10.1
Requires-Dist: python-dateutil>=2.9.0.post0
Requires-Dist: numpy>=1.23.4
Requires-Dist: pycryptodome>=3.17
Dynamic: author
Dynamic: classifier
Dynamic: description
Dynamic: description-content-type
Dynamic: home-page
Dynamic: license-file
Dynamic: requires-dist
Dynamic: summary
